ai/__init__.py
ai/starlake/__init__.py
ai/starlake/airflow/__init__.py
ai/starlake/airflow/starlake_airflow_api.py
ai/starlake/airflow/starlake_airflow_job.py
ai/starlake/airflow/starlake_airflow_options.py
ai/starlake/airflow/starlake_airflow_orchestration.py
ai/starlake/airflow/aws/__init__.py
ai/starlake/airflow/aws/starlake_airflow_fargate_job.py
ai/starlake/airflow/bash/__init__.py
ai/starlake/airflow/bash/starlake_airflow_bash_job.py
ai/starlake/airflow/gcp/__init__.py
ai/starlake/airflow/gcp/starlake_airflow_cloud_run_job.py
ai/starlake/airflow/gcp/starlake_airflow_dataproc_job.py
starlake_airflow-0.5.0.dist-info/licenses/LICENSE
starlake_airflow-0.5.0.dist-info/METADATA
starlake_airflow-0.5.0.dist-info/WHEEL
starlake_airflow-0.5.0.dist-info/top_level.txt
starlake_airflow-0.5.0.dist-info/RECORD
