Metadata-Version: 2.4
Name: starlake-airflow
Version: 0.5.0
Summary: Starlake Python Distribution For Airflow
Author: Stéphane Manciot
Author-email: stephane.manciot@gmail.com
License: Apache 2.0
Requires-Python: >=3.8
License-File: LICENSE
Requires-Dist: starlake-orchestration~=0.4
Provides-Extra: airflow
Requires-Dist: airflow>=2.10.0; extra == "airflow"
Provides-Extra: shell
Provides-Extra: gcp
Provides-Extra: aws
Provides-Extra: azure
Dynamic: author
Dynamic: author-email
Dynamic: description
Dynamic: description-content-type
Dynamic: license
Dynamic: license-file
Dynamic: provides-extra
Dynamic: requires-dist
Dynamic: requires-python
Dynamic: summary
